README.md
setup.py
kaptain/__init__.py
kaptain/captain.py
kaptain/logger.py
kaptain/main.py
kaptain/report.py
kaptain/ws.py
kaptain.egg-info/PKG-INFO
kaptain.egg-info/SOURCES.txt
kaptain.egg-info/dependency_links.txt
kaptain.egg-info/entry_points.txt
kaptain.egg-info/not-zip-safe
kaptain.egg-info/requires.txt
kaptain.egg-info/top_level.txt
kaptain/fetch_log/__init__.py
kaptain/fetch_log/command.py