Metadata-Version: 2.1
Name: kaptain
Version: 0.1.3
Summary: A modern SRE tool
Home-page: https://github.com/wangwenpei/kaptain
Author: WANG WENPEI
Author-email: stormxx@1024.engineer
License: MIT
Download-URL: https://github.com/wangwenpei/kaptain/tarball/master
Keywords: captain,kubernetes,k8s
Platform: UNKNOWN
Provides-Extra: test
Provides-Extra: dev
Provides-Extra: kaptain
